README.md
setup.cfg
setup.py
UserAgent_Pool/UserAgent_Pool.py
UserAgent_Pool.egg-info/PKG-INFO
UserAgent_Pool.egg-info/SOURCES.txt
UserAgent_Pool.egg-info/dependency_links.txt
UserAgent_Pool.egg-info/top_level.txt