Metadata-Version: 1.1
Name: UserAgent-Pool
Version: 1.0.5
Summary: Use for randomly get header
Home-page: https://github.com/MuFanChang/UserAgentPool
Author: Steven Chang
Author-email: s8110282004@gmail.com
License: UNKNOWN
Download-URL: https://github.com/MuFanChang/UserAgentPool/releases/tag/v1.0.5
Keywords: UserAgent,header
Platform: UNKNOWN
